setup.py
skyext/__init__.py
skyext/alchemy_db.py
skyext/cache.py
skyext/exts.py
skyext/session.py
skyext.egg-info/PKG-INFO
skyext.egg-info/SOURCES.txt
skyext.egg-info/dependency_links.txt
skyext.egg-info/requires.txt
skyext.egg-info/top_level.txt
skyext/base_class/__init__.py
skyext/base_class/action_base.py
skyext/base_class/main_base.py
skyext/base_class/model_base.py
skyext/db/__init__.py
skyext/db/es_db.py
skyext/db/postgre_db.py
skyext/db/redis_db.py
skyext/decorator/__init__.py
skyext/decorator/db_session.py
skyext/decorator/validator.py
skyext/utils/__init__.py
skyext/utils/db_utils.py
skyext/utils/file_utils.py
skyext/utils/reflect_utils.py
skyext/utils/resp_utils.py
skyext/validator/__init__.py
skyext/validator/base_form.py
skyext/validator/field.py
skyext/validator/validators.py
skyext/validator/parse/__init__.py
skyext/validator/parse/make_form.py
skyext/validator/parse/validator_forms.py