Metadata-Version: 1.0
Name: skyext
Version: 1.0.2.3
Summary: ext sdk
Home-page: UNKNOWN
Author: skyeye
Author-email: skyeye@gmail.com
License: MIT Licence
Keywords: test,ext
Platform: any
